PyFVCOM/__init__.py
PyFVCOM/buoy.py
PyFVCOM/coast.py
PyFVCOM/coordinate.py
PyFVCOM/current.py
PyFVCOM/grid.py
PyFVCOM/interpolate.py
PyFVCOM/ocean.py
PyFVCOM/plot.py
PyFVCOM/preproc.py
PyFVCOM/read.py
PyFVCOM/stats.py
PyFVCOM/tidal_ellipse.py
PyFVCOM/tide.py
PyFVCOM/validation.py
PyFVCOM/ctd/__init__.py
PyFVCOM/grid/__init__.py
PyFVCOM/grid/_grid.py
PyFVCOM/utilities/__init__.py
PyFVCOM/utilities/general.py
PyFVCOM/utilities/grid.py
PyFVCOM/utilities/time.py
PyFVCOM-2.2.0.dist-info/METADATA
PyFVCOM-2.2.0.dist-info/RECORD
PyFVCOM-2.2.0.dist-info/WHEEL
PyFVCOM-2.2.0.dist-info/top_level.txt
