Metadata-Version: 2.1
Name: PyFVCOM
Version: 2.2.0
Summary: PyFVCOM is a collection of various tools which can be used to generate inputs files and interact with FVCOM outputs.
Home-page: https://gitlab.ecosystem-modelling.pml.ac.uk/fvcom/PyFVCOM
Author: Pierre Cazenave
Author-email: pica@pml.ac.uk
License: MIT
Download-URL: http://gitlab.em.pml.ac.uk/fvcom/PyFVCOM/repository/archive.tar.gz?ref=2.2.0
Keywords: fvcom,unstructured grid,mesh
Platform: any
Requires-Dist: jdcal
Requires-Dist: lxml
Requires-Dist: matplotlib
Requires-Dist: netCDF4
Requires-Dist: networkx
Requires-Dist: numpy (>=1.13.0)
Requires-Dist: pandas
Requires-Dist: xlsxwriter
Requires-Dist: pyproj
Requires-Dist: pytz
Requires-Dist: scipy
Requires-Dist: pyshp
Requires-Dist: UTide
Requires-Dist: shapely
Requires-Dist: descartes
